autocode/__init__.py
autocode/container.py
autocode/controller.py
autocode/dashboard.py
autocode/datastore.py
autocode/gateway.py
autocode/model.py
autocode/router.py
autocode/setting.py
autocode/use_case.py
autocode_py-0.0.1.post9.dist-info/METADATA
autocode_py-0.0.1.post9.dist-info/WHEEL
autocode_py-0.0.1.post9.dist-info/top_level.txt
autocode_py-0.0.1.post9.dist-info/RECORD
