Metadata-Version: 2.1
Name: autocode-py
Version: 0.0.1.post9
Summary: autocode: Auto Code Improvement by Metrics Optimization.
Home-page: https://github.com/muazhari/autocode
Author: muazhari
Classifier: Intended Audience :: Developers
Classifier: Operating System :: POSIX :: Linux
Classifier: Programming Language :: Python :: 3
Classifier: Programming Language :: Python :: 3.10
Classifier: Programming Language :: Python :: 3.11
Classifier: Topic :: Software Development
Classifier: Topic :: Scientific/Engineering
Requires-Dist: pymoo
Requires-Dist: pydantic-settings
Requires-Dist: fastapi
Requires-Dist: dependency-injector
Requires-Dist: ray
Requires-Dist: matplotlib <3.9.0
Requires-Dist: sqlmodel
Requires-Dist: dill
Requires-Dist: streamlit
Requires-Dist: numpy <2
Requires-Dist: python-on-whales
Requires-Dist: uvicorn
Requires-Dist: langchain
Requires-Dist: langchain-openai >=0.1.21rc1
Requires-Dist: langgraph
